odoo/addons/website_sale_financial_risk/README.rst
odoo/addons/website_sale_financial_risk/__init__.py
odoo/addons/website_sale_financial_risk/__manifest__.py
odoo/addons/website_sale_financial_risk/controllers/__init__.py
odoo/addons/website_sale_financial_risk/controllers/main.py
odoo/addons/website_sale_financial_risk/data/payment_provider_data.xml
odoo/addons/website_sale_financial_risk/i18n/website_sale_financial_risk.pot
odoo/addons/website_sale_financial_risk/models/__init__.py
odoo/addons/website_sale_financial_risk/models/payment_provider.py
odoo/addons/website_sale_financial_risk/models/payment_transaction.py
odoo/addons/website_sale_financial_risk/readme/CONFIGURE.rst
odoo/addons/website_sale_financial_risk/readme/CONTRIBUTORS.rst
odoo/addons/website_sale_financial_risk/readme/DESCRIPTION.rst
odoo/addons/website_sale_financial_risk/readme/USAGE.rst
odoo/addons/website_sale_financial_risk/static/description/icon.png
odoo/addons/website_sale_financial_risk/static/description/index.html
odoo/addons/website_sale_financial_risk/static/img/icon.png
odoo/addons/website_sale_financial_risk/static/img/icon.svg
odoo/addons/website_sale_financial_risk/static/src/js/post_processing.js
odoo/addons/website_sale_financial_risk/templates/payment_custom_templates.xml
odoo/addons/website_sale_financial_risk/templates/website_sale_templates.xml
odoo_addon_website_sale_financial_risk-16.0.1.0.0.3.dist-info/METADATA
odoo_addon_website_sale_financial_risk-16.0.1.0.0.3.dist-info/WHEEL
odoo_addon_website_sale_financial_risk-16.0.1.0.0.3.dist-info/top_level.txt
odoo_addon_website_sale_financial_risk-16.0.1.0.0.3.dist-info/RECORD
